geolake/__init__.py
geolake/cache.py
geolake/client.py
geolake-0.1.0b0.dist-info/LICENSE
geolake-0.1.0b0.dist-info/METADATA
geolake-0.1.0b0.dist-info/WHEEL
geolake-0.1.0b0.dist-info/top_level.txt
geolake-0.1.0b0.dist-info/RECORD
