Metadata-Version: 2.1
Name: geolake
Version: 0.1.0b0
Summary: Python client for geolake
Author-email: geolake Contributors <geolake@googlegroups.com>
Maintainer-email: geolake Contributors <geolake@googlegroups.com>
License: Apache License
Project-URL: Homepage, https://geo-lake.github.io
Project-URL: Documentation, https://geo-lake.github.io
Project-URL: Repository, https://github.com/CMCC-Foundation/geolake.git
Keywords: Earth science,data analysis
Classifier: Development Status :: 4 - Beta
Classifier: Environment :: Web Environment
Classifier: Intended Audience :: Science/Research
Classifier: License :: OSI Approved :: Apache Software License
Classifier: Natural Language :: English
Classifier: Operating System :: OS Independent
Classifier: Programming Language :: Python :: 3
Classifier: Topic :: Scientific/Engineering
Requires-Python: >=3.7
License-File: LICENSE
Requires-Dist: netCDF4 >=1.5.3
Requires-Dist: scipy >=1.5.2
Requires-Dist: requests >=2.23.0
Requires-Dist: geokube >=0.2.6b2
